totptray/__init__.py
totptray/__main__.py
totptray/totptray.py
totptray-1.2.2.dist-info/LICENSE
totptray-1.2.2.dist-info/METADATA
totptray-1.2.2.dist-info/WHEEL
totptray-1.2.2.dist-info/entry_points.txt
totptray-1.2.2.dist-info/top_level.txt
totptray-1.2.2.dist-info/RECORD
