Metadata-Version: 2.1
Name: totptray
Version: 1.2.2
Summary: A simple tray icon tool with a TOTP implementation.
Home-page: https://github.com/McCzarny/totptray
Author: Maciej Czarnecki
Author-email: mcczarny@gmail.com
License: The Unlicense
Platform: UNKNOWN
Classifier: License :: OSI Approved :: The Unlicense (Unlicense)
Classifier: Programming Language :: Python :: 3
Classifier: Programming Language :: Python :: 3.7
License-File: LICENSE
Requires-Dist: pyperclip
Requires-Dist: pystray
Requires-Dist: pyotp
